odoo/addons/ssi_hr_expense_account_cash_advance/README.rst
odoo/addons/ssi_hr_expense_account_cash_advance/__init__.py
odoo/addons/ssi_hr_expense_account_cash_advance/__manifest__.py
odoo/addons/ssi_hr_expense_account_cash_advance/i18n/ssi_hr_expense_account_cash_advance.pot
odoo/addons/ssi_hr_expense_account_cash_advance/models/__init__.py
odoo/addons/ssi_hr_expense_account_cash_advance/models/employee_expense_account.py
odoo/addons/ssi_hr_expense_account_cash_advance/models/hr_cash_advance_settlement.py
odoo/addons/ssi_hr_expense_account_cash_advance/models/hr_cash_advance_settlement_line.py
odoo/addons/ssi_hr_expense_account_cash_advance/static/description/icon.png
odoo/addons/ssi_hr_expense_account_cash_advance/static/description/icon_timesheet.png
odoo/addons/ssi_hr_expense_account_cash_advance/views/employee_expense_account_view.xml
odoo/addons/ssi_hr_expense_account_cash_advance/views/hr_cash_advance_settlement.xml
odoo14_addon_ssi_hr_expense_account_cash_advance-14.0.1.3.0.dist-info/METADATA
odoo14_addon_ssi_hr_expense_account_cash_advance-14.0.1.3.0.dist-info/WHEEL
odoo14_addon_ssi_hr_expense_account_cash_advance-14.0.1.3.0.dist-info/top_level.txt
odoo14_addon_ssi_hr_expense_account_cash_advance-14.0.1.3.0.dist-info/RECORD
