Metadata-Version: 2.1
Name: odoo14-addon-ssi_hr_expense_account_cash_advance
Version: 14.0.1.3.0
Summary: Employee Expense Account - Cash Advance Integration
Home-page: https://simetri-sinergi.id
Author: OpenSynergy Indonesia, PT. Simetri Sinergi Indonesia
License: AGPL-3
Classifier: Programming Language :: Python
Classifier: Framework :: Odoo
Classifier: Framework :: Odoo :: 14.0
Classifier: License :: OSI Approved :: GNU Affero General Public License v3
Requires-Python: >=3.6
Requires-Dist: odoo14-addon-ssi-hr-cash-advance
Requires-Dist: odoo14-addon-ssi-hr-expense-account
Requires-Dist: odoo<14.1dev,>=14.0a
